pijp/__init__.py
pijp/cli.py
pijp/commands/__init__.py
pijp/commands/pipelines.py
pijp/commands/plan.py
pijp/commands/run.py
pijp/config/__init__.py
pijp/config/manifest.py
pijp/config/pipeline.py
pijp/config/jobs/__init__.py
pijp/config/jobs/base.py
pijp/config/jobs/container.py
pijp/config/jobs/shell.py
pijp/report/__init__.py
pijp/report/runner.py
pijp/report/system.py
pijp/report/vcs/__init__.py
pijp/report/vcs/git.py
pijp/utils/__init__.py
pijp/utils/colors.py
pijp/utils/graph.py
pijp/utils/ids.py
pijp/utils/scripts.py
pijp/utils/vars.py
pijp-0.1.4.dist-info/LICENSE
pijp-0.1.4.dist-info/METADATA
pijp-0.1.4.dist-info/WHEEL
pijp-0.1.4.dist-info/entry_points.txt
pijp-0.1.4.dist-info/top_level.txt
pijp-0.1.4.dist-info/RECORD
