Metadata-Version: 2.1
Name: pijp
Version: 0.1.4
Summary: Local CI pipelines
License-File: LICENSE
Requires-Dist: click ==8.1.7
Requires-Dist: contexttimer ==0.3.3
Requires-Dist: docker ==7.0.0
Requires-Dist: func-timeout ==4.3.5
Requires-Dist: gitpython ==3.1.41
Requires-Dist: humanize ==4.9.0
Requires-Dist: pydantic ==2.5.3
Requires-Dist: python-dotenv ==1.0.0
Requires-Dist: pyyaml ==6.0.1
Requires-Dist: rich ==13.7.0
Requires-Dist: simpleeval ==0.9.13
Provides-Extra: dev
Requires-Dist: black ==23.12.1 ; extra == 'dev'
Requires-Dist: mypy ==1.8.0 ; extra == 'dev'
Requires-Dist: pylint ==3.0.3 ; extra == 'dev'
Requires-Dist: pytest-cov ==4.1.0 ; extra == 'dev'
Requires-Dist: pytest ==7.4.3 ; extra == 'dev'
